terrapyst/__init__.py
terrapyst/_version.py
terrapyst/apply_log.py
terrapyst/authentication.py
terrapyst/exceptions.py
terrapyst/mixins.py
terrapyst/plan.py
terrapyst/py.typed
terrapyst/workspace.py
tests/__init__.py
tests/conftest.py
tests/test_apply_logs.py
tests/test_plan.py
tests/test_workspace.py
terrapyst-0.4.1.dist-info/LICENSE
terrapyst-0.4.1.dist-info/METADATA
terrapyst-0.4.1.dist-info/WHEEL
terrapyst-0.4.1.dist-info/top_level.txt
terrapyst-0.4.1.dist-info/RECORD
